{
    "swagger": "2.0",
    "info": {
        "title": "Mi API de peliculas tipo Neflis",
        "version": "1.0.0"
    },
    "paths": {
        "/api/v1/users": {
            "get": {
                "responses": {
                    "200": {
                        "description": "Obtener todos mis usuarios"
                    },
                    "400" : {
                        "description": "Ocurrio un error al intentar obtener todos los usuarios"
                    }
                }
            }
        }
    }
}